{"generated_at":"2026-01-25T15:40:30.866133+00:00","source_file":"results/nd2_benchmark_final/decomp_sr_results_20260113_002948.csv","selection_rule":"best final_r2 per scenario (gplearn preferred)","scenarios":[{"scenario":"exp_plus_sine","sample_id":"exp_plus_sine_67c6a1e7","oracle_trend_expr":"div(-0.692, ((x0 - -0.917) - -0.917))","oracle_seasonal_expr":"0.002","rows":[{"decomp_method":"none","sr_method":"gplearn","final_r2":-0.00010575727912054411,"success":true,"trend_expr":"mul(mul(-0.261, mul(-0.006, ((0.134 * -0.528) * x0))), mul(mul(mul(-0.006, mul(mul(mul(sin(-0.006), ((0.134 * -0.528) * x0)), -0.753), x0)), sin(-0.753)), x0))","seasonal_expr":"mul(sin(div(((x0 + x0) + (-0.920 * x0)), div((0.548 + 0.605), (0.964 * x0)))), div(mul(sin((x0 - x0)), cos(cos(-0.543))), sin(div((x0 * x0), (x0 + x0)))))","full_expr":"(mul(mul(-0.261, mul(-0.006, ((0.134 * -0.528) * x0))), mul(mul(mul(-0.006, mul(mul(mul(sin(-0.006), ((0.134 * -0.528) * x0)), -0.753), x0)), sin(-0.753)), x0))) + (mul(sin(div(((x0 + x0) + (-0.920 * x0)), div((0.548 + 0.605), (0.964 * x0)))), div(mul(sin((x0 - x0)), cos(cos(-0.543))), sin(div((x0 * x0), (x0 + x0))))))"},{"decomp_method":"none","sr_method":"nd2","final_r2":0.0,"success":false,"trend_expr":"0","seasonal_expr":"","full_expr":"","trend_expr_latex":"0","seasonal_expr_latex":"","full_expr_latex":""},{"decomp_method":"stl","sr_method":"gplearn","final_r2":-7.865792927663762e-06,"success":true,"trend_expr":"div(-0.960, (x0 + cos(x0)))","seasonal_expr":"x0 - x0","full_expr":"(div(-0.960, (x0 + cos(x0)))) + (x0 - x0)"},{"decomp_method":"stl","sr_method":"nd2","final_r2":0.0,"success":false,"trend_expr":"(-0.3420+((0.0040*t)**2))","seasonal_expr":"","full_expr":"","trend_expr_latex":"1.6 \\cdot 10^{-5} t^{2} - 0.342","seasonal_expr_latex":"","full_expr_latex":""}]},{"scenario":"linear_plus_multi_harmonic","sample_id":"linear_plus_multi_harmonic_a1d0c6e8","oracle_trend_expr":"sin(div(div(div(add(cos((x0 * -0.016)), cos(mul((-0.412 + x0), -0.016))), (-0.412 + x0)), div((-0.016 - -0.114), (x0 * -0.016))), sin(cos(-0.727))))","oracle_seasonal_expr":"x0 - x0","rows":[{"decomp_method":"none","sr_method":"gplearn","final_r2":0.0,"success":true,"trend_expr":"mul(sub(add(add(add(add(add(add(add(((x0 + -0.896) + -0.896), ((-0.948 / 0.389) / 0.389)), -0.896), -0.896), -0.896), -0.896), (-0.948 / 0.389)), -0.896), (x0 * cos(-0.592))), (-0.057 * -0.138))","seasonal_expr":"(-0.130 / x0) *  (x0 - x0)","full_expr":"(mul(sub(add(add(add(add(add(add(add(((x0 + -0.896) + -0.896), ((-0.948 / 0.389) / 0.389)), -0.896), -0.896), -0.896), -0.896), (-0.948 / 0.389)), -0.896), (x0 * cos(-0.592))), (-0.057 * -0.138))) + ((-0.130 / x0) *  (x0 - x0))"},{"decomp_method":"none","sr_method":"nd2","final_r2":0.0,"success":false,"trend_expr":"(0.0048*(-127.5000+t))","seasonal_expr":"","full_expr":"","trend_expr_latex":"0.0048 t - 0.612","seasonal_expr_latex":"","full_expr_latex":""},{"decomp_method":"stl","sr_method":"gplearn","final_r2":-0.0008200366049238017,"success":true,"trend_expr":"mul(-0.992, div(0.992, ((x0 - -0.813) + cos(x0))))","seasonal_expr":"0.009","full_expr":"(mul(-0.992, div(0.992, ((x0 - -0.813) + cos(x0))))) + (0.009)"},{"decomp_method":"stl","sr_method":"nd2","final_r2":0.0,"success":false,"trend_expr":"(0.0049*(t+-127.8732))","seasonal_expr":"","full_expr":"","trend_expr_latex":"0.0049 t - 0.62657868","seasonal_expr_latex":"","full_expr_latex":""}]},{"scenario":"linear_plus_sine","sample_id":"linear_plus_sine_c0c7c76d","oracle_trend_expr":"sin(sin(sin(sin(sin(sin(div(cos(cos(add(((0.796 / x0) * -0.944), -0.154))), add(sin(div(div((0.497 * x0), x0), add(((0.796 / x0) * -0.944), -0.154))), -0.154))))))))","oracle_seasonal_expr":"0.006","rows":[{"decomp_method":"none","sr_method":"gplearn","final_r2":-1.8747830954568556e-05,"success":true,"trend_expr":"sin(sin(sin(sin(div(0.881, (-0.009 / (0.207 / x0)))))))","seasonal_expr":"(-0.821 / x0) *  (x0 - x0)","full_expr":"(sin(sin(sin(sin(div(0.881, (-0.009 / (0.207 / x0)))))))) + ((-0.821 / x0) *  (x0 - x0))"},{"decomp_method":"none","sr_method":"nd2","final_r2":0.0,"success":false,"trend_expr":"(0.0057*(t+-127.0661))","seasonal_expr":"","full_expr":"","trend_expr_latex":"0.0057 t - 0.72427677","seasonal_expr_latex":"","full_expr_latex":""},{"decomp_method":"stl","sr_method":"gplearn","final_r2":-3.092473386190342e-05,"success":true,"trend_expr":"sin(sin(sin(sin(sin(sin(div(sin(sin(sin(div(((0.877 / x0) / (0.097 / x0)), 0.217)))), 0.217)))))))","seasonal_expr":"x0 - x0","full_expr":"(sin(sin(sin(sin(sin(sin(div(sin(sin(sin(div(((0.877 / x0) / (0.097 / x0)), 0.217)))), 0.217)))))))) + (x0 - x0)"},{"decomp_method":"stl","sr_method":"nd2","final_r2":0.0,"success":false,"trend_expr":"((126.8394-t)*-0.0053)","seasonal_expr":"","full_expr":"","trend_expr_latex":"0.0053 t - 0.67224882","seasonal_expr_latex":"","full_expr_latex":""}]},{"scenario":"quadratic_plus_sine","sample_id":"quadratic_plus_sine_c0c7c76d","oracle_trend_expr":"sin(sin(((0.785 / 0.068) / (x0 / 0.613))))","oracle_seasonal_expr":"-0.085 * -0.174","rows":[{"decomp_method":"none","sr_method":"gplearn","final_r2":-1.052481141261552e-05,"success":true,"trend_expr":"sin(div(0.975, mul(((x0 * 0.519) * 0.519), 0.519)))","seasonal_expr":"sin((x0 - x0))","full_expr":"(sin(div(0.975, mul(((x0 * 0.519) * 0.519), 0.519)))) + (sin((x0 - x0)))"},{"decomp_method":"none","sr_method":"nd2","final_r2":0.0,"success":false,"trend_expr":"((127.7780-t)*0.0066)","seasonal_expr":"","full_expr":"","trend_expr_latex":"0.8433348 - 0.0066 t","seasonal_expr_latex":"","full_expr_latex":""},{"decomp_method":"stl","sr_method":"gplearn","final_r2":-4.0852332123808566e-06,"success":true,"trend_expr":"add(div(cos(sin((sin(x0) - (x0 * -0.673)))), (0.311 * x0)), add(div(sin(sin(mul((x0 * -0.273), mul(0.145, add(div(sin(sin(((x0 * -0.273) * (0.145 * -0.013)))), -0.959), add(-0.013, div(-0.627, sin(((x0 * -0.273) * (0.145 * -0.013)))))))))), sub((-0.959 + x0), x0)), sin((0.145 * -0.013))))","seasonal_expr":"(0.685 / x0) *  (x0 - x0)","full_expr":"(add(div(cos(sin((sin(x0) - (x0 * -0.673)))), (0.311 * x0)), add(div(sin(sin(mul((x0 * -0.273), mul(0.145, add(div(sin(sin(((x0 * -0.273) * (0.145 * -0.013)))), -0.959), add(-0.013, div(-0.627, sin(((x0 * -0.273) * (0.145 * -0.013)))))))))), sub((-0.959 + x0), x0)), sin((0.145 * -0.013))))) + ((0.685 / x0) *  (x0 - x0))"},{"decomp_method":"stl","sr_method":"nd2","final_r2":0.0,"success":false,"trend_expr":"(-0.0069*(t-127.8726))","seasonal_expr":"","full_expr":"","trend_expr_latex":"0.88232094 - 0.0069 t","seasonal_expr_latex":"","full_expr_latex":""}]}]}
